app/__init__.py
app/connection.py
streamlit_sample_connector-0.0.1.dist-info/METADATA
streamlit_sample_connector-0.0.1.dist-info/WHEEL
streamlit_sample_connector-0.0.1.dist-info/top_level.txt
streamlit_sample_connector-0.0.1.dist-info/RECORD
